xplan/__init__.py
xplan/__main__.py
xplan/display_cursor.py
xplan-0.0.12.dist-info/METADATA
xplan-0.0.12.dist-info/WHEEL
xplan-0.0.12.dist-info/top_level.txt
xplan-0.0.12.dist-info/RECORD
