Metadata-Version: 2.1
Name: xplan
Version: 0.0.12
Summary: UNKNOWN
Home-page: UNKNOWN
Author: shinhwagk
Author-email: shinhwagk@outlook.com
License: UNKNOWN
Platform: UNKNOWN
Requires-Dist: cx-Oracle
